nextpy/__init__.py
nextpy/auth.py
nextpy/builder.py
nextpy/cli.py
nextpy/components.py
nextpy/config.py
nextpy/db.py
nextpy/dev_server.py
nextpy/dev_tools.py
nextpy/errors.py
nextpy/hooks.py
nextpy/hooks_provider.py
nextpy/hooks_provider_new.py
nextpy/jsx.py
nextpy/jsx_preprocessor.py
nextpy/jsx_transformer.py
nextpy/main.py
nextpy/performance.py
nextpy/plugins.py
nextpy/py.typed
nextpy/security.py
nextpy/true_jsx.py
nextpy/websocket.py
nextpy/components/__init__.py
nextpy/components/feedback.py
nextpy/components/form.py
nextpy/components/head.py
nextpy/components/hooks_provider.py
nextpy/components/image.py
nextpy/components/layout.py
nextpy/components/link.py
nextpy/components/loader.py
nextpy/components/navigation.py
nextpy/components/toast.py
nextpy/components/ui.py
nextpy/components/visual.py
nextpy/components/debug/AutoDebug.py
nextpy/components/debug/DebugIcon.py
nextpy/components/debug/DebugIconFixed.py
nextpy/core/__init__.py
nextpy/core/builder.py
nextpy/core/component_renderer.py
nextpy/core/component_router.py
nextpy/core/data_fetching.py
nextpy/core/demo_pages_simple.py
nextpy/core/demo_router.py
nextpy/core/renderer.py
nextpy/core/router.py
nextpy/core/sync.py
nextpy/plugins/__init__.py
nextpy/plugins/base.py
nextpy/plugins/builtin.py
nextpy/plugins/config.py
nextpy/server/__init__.py
nextpy/server/app.py
nextpy/server/debug.py
nextpy/server/middleware.py
nextpy/utils/__init__.py
nextpy/utils/cache.py
nextpy/utils/email.py
nextpy/utils/file_upload.py
nextpy/utils/logging.py
nextpy/utils/search.py
nextpy/utils/seo.py
nextpy/utils/validators.py
nextpy_framework-2.4.6.dist-info/licenses/LICENSE
nextpy_framework-2.4.6.dist-info/METADATA
nextpy_framework-2.4.6.dist-info/WHEEL
nextpy_framework-2.4.6.dist-info/entry_points.txt
nextpy_framework-2.4.6.dist-info/top_level.txt
nextpy_framework-2.4.6.dist-info/RECORD
