Metadata-Version: 2.4
Name: nextpy-framework
Version: 2.4.6
Summary: A Python web framework inspired by Next.js with file-based routing, SSR, and SSG and more
Author: NextPy Team
License: MIT
Project-URL: Homepage, https://github.com/IBRAHIMFONYUY/nextpy-framework
Project-URL: Documentation, https://nextpy-framework.readthedocs.io
Project-URL: Repository, https://github.com/IBRAHIMFONYUY/nextpy-framework
Keywords: web framework,nextjs,fastapi,ssr,ssg,file-based routing,htmx,jinja2
Classifier: Development Status :: 4 - Beta
Classifier: Intended Audience :: Developers
Classifier: License :: OSI Approved :: MIT License
Classifier: Programming Language :: Python :: 3
Classifier: Programming Language :: Python :: 3.11
Classifier: Programming Language :: Python :: 3.12
Classifier: Framework :: FastAPI
Classifier: Topic :: Internet :: WWW/HTTP :: HTTP Servers
Classifier: Topic :: Software Development :: Libraries :: Application Frameworks
Requires-Python: >=3.11
License-File: LICENSE
Requires-Dist: aiofiles>=25.1.0
Requires-Dist: click>=8.3.1
Requires-Dist: fastapi>=0.122.0
Requires-Dist: httpx>=0.28.1
Requires-Dist: jinja2>=3.1.6
Requires-Dist: pillow>=12.0.0
Requires-Dist: pydantic>=2.12.5
Requires-Dist: python-multipart>=0.0.20
Requires-Dist: uvicorn>=0.38.0
Requires-Dist: watchdog>=6.0.0
Requires-Dist: python-dotenv>=1.2.1
Requires-Dist: sqlalchemy>=2.0.44
Provides-Extra: dev
Requires-Dist: pytest>=7.0; extra == "dev"
Requires-Dist: pytest-asyncio>=0.21.0; extra == "dev"
Requires-Dist: black>=23.0; extra == "dev"
Requires-Dist: mypy>=1.0; extra == "dev"
Dynamic: license-file
